mox3/__init__.py
mox3/fixture.py
mox3/mox.py
mox3/stubout.py
mox3/tests/__init__.py
mox3/tests/mox_helper.py
mox3/tests/stubout_helper.py
mox3/tests/test_mox.py
mox3/tests/test_stubout.py
mox3-1.1.0.dist-info/AUTHORS
mox3-1.1.0.dist-info/COPYING.txt
mox3-1.1.0.dist-info/METADATA
mox3-1.1.0.dist-info/WHEEL
mox3-1.1.0.dist-info/pbr.json
mox3-1.1.0.dist-info/top_level.txt
mox3-1.1.0.dist-info/RECORD
